pyzabbix/__init__.py
pyzabbix/api.py
pyzabbix/sender.py
zabbix-2.0.2.dist-info/LICENSE
zabbix-2.0.2.dist-info/METADATA
zabbix-2.0.2.dist-info/WHEEL
zabbix-2.0.2.dist-info/top_level.txt
zabbix-2.0.2.dist-info/RECORD
